EncodedStrings/__init__.py
EncodedStrings/main_module.py
EncodedStrings/submodules/__init__.py
EncodedStrings/submodules/async_functions.py
EncodedStrings/submodules/sync_functions.py
EncodedStrings-0.0.1.dist-info/LICENSE
EncodedStrings-0.0.1.dist-info/METADATA
EncodedStrings-0.0.1.dist-info/WHEEL
EncodedStrings-0.0.1.dist-info/top_level.txt
EncodedStrings-0.0.1.dist-info/RECORD
