Metadata-Version: 2.1
Name: EncodedStrings
Version: 0.0.1
Summary: A utility for encoding strings
Home-page: https://github.com/NightMareDeadTrix/EncodedString
Author: NightMareDeadTrix
Author-email: UNKNOWN
License: MIT
Platform: UNKNOWN
